jrdev/__init__.py
jrdev/__main__.py
jrdev/cli.py
jrdev/logger.py
jrdev/agents/__init__.py
jrdev/agents/agent_tools.py
jrdev/agents/code_agent.py
jrdev/agents/router_agent.py
jrdev/agents/pipeline/__init__.py
jrdev/agents/pipeline/analyze_phase.py
jrdev/agents/pipeline/execute_phase.py
jrdev/agents/pipeline/fetch_context_phase.py
jrdev/agents/pipeline/plan_phase.py
jrdev/agents/pipeline/review_phase.py
jrdev/agents/pipeline/stage.py
jrdev/agents/pipeline/validate_phase.py
jrdev/commands/__init__.py
jrdev/commands/addcontext.py
jrdev/commands/asyncsend.py
jrdev/commands/cancel.py
jrdev/commands/clearcontext.py
jrdev/commands/code.py
jrdev/commands/compact.py
jrdev/commands/cost.py
jrdev/commands/exit.py
jrdev/commands/git.py
jrdev/commands/git_config.py
jrdev/commands/git_pr.py
jrdev/commands/help.py
jrdev/commands/init.py
jrdev/commands/keys.py
jrdev/commands/migrate.py
jrdev/commands/model.py
jrdev/commands/modelprofile.py
jrdev/commands/models.py
jrdev/commands/projectcontext.py
jrdev/commands/provider.py
jrdev/commands/routeragent.py
jrdev/commands/stateinfo.py
jrdev/commands/tasks.py
jrdev/commands/thread.py
jrdev/commands/viewcontext.py
jrdev/commands/debug/__init__.py
jrdev/commands/debug/git.py
jrdev/commands/debug/models.py
jrdev/config/api_providers.json
jrdev/config/model_list.json
jrdev/config/profile_strings.json
jrdev/core/__init__.py
jrdev/core/application.py
jrdev/core/clients.py
jrdev/core/commands.py
jrdev/core/exceptions.py
jrdev/core/state.py
jrdev/core/tool_call.py
jrdev/core/usage.py
jrdev/core/user_settings.py
jrdev/docs/__init__.py
jrdev/docs/git_explanation.md
jrdev/file_operations/__init__.py
jrdev/file_operations/add.py
jrdev/file_operations/apply_changes.py
jrdev/file_operations/confirmation.py
jrdev/file_operations/delete.py
jrdev/file_operations/diff_markup.py
jrdev/file_operations/diff_utils.py
jrdev/file_operations/file_lock.py
jrdev/file_operations/file_utils.py
jrdev/file_operations/find_function.py
jrdev/file_operations/insert.py
jrdev-0.1.11a0.dist-info/licenses/LICENSE
jrdev-0.1.11a0.dist-info/METADATA
jrdev-0.1.11a0.dist-info/WHEEL
jrdev-0.1.11a0.dist-info/entry_points.txt
jrdev-0.1.11a0.dist-info/top_level.txt
jrdev-0.1.11a0.dist-info/RECORD
